{
	"1": {
		"251d4e": "6a445c",
		"434475": "e7a6c9",
		"303360": "ad6f83",
		"646ca8": "ffdeeb",
		"4d5488": "f4a0b9",
		"010101": "010101",
		"ffa8a8": "ffc586",
		"f30101": "df7b10",
		"4e4150": "57445a",
		"2c2b58": "845195",
		"18173d": "4b2a5e",
		"3e3d6d": "bc7dc3",
		"2e262f": "2e262f"
	},
	"2": {
		"251d4e": "547585",
		"434475": "d8e2ed",
		"303360": "99cae0",
		"646ca8": "aedcf5",
		"4d5488": "99bbde",
		"010101": "010101",
		"ffa8a8": "ff4afc",
		"f30101": "ba00e8",
		"4e4150": "8b98d6",
		"2c2b58": "93bbcf",
		"18173d": "536c8a",
		"3e3d6d": "93bad9",
		"2e262f": "485987",
		"d70143": "ba00e8",
		"7a185f": "6b1b70"
	}
}